{"numFound": 5, "start": 0, "numFoundExact": true, "num_found": 5, "docs": [{"key": "/works/OL17610986W", "title": "The Wonderful Wizard of Oz", "author_name": ["L. Frank Baum"]}, {"key": "/works/OL17623412W", "title": "The Marvelous Land of Oz", "author_name": ["L. Frank Baum"]}, {"key": "/works/OL17798838W", "title": "Ozma of Oz", "author_name": ["L. Frank Baum"]}, {"key": "/works/OL17844203W", "title": "Dorothy and the Wizard in Oz", "author_name": ["L. Frank Baum"]}, {"key": "/works/OL17922359W", "title": "The Road to Oz", "author_name": ["L. Frank Baum"]}]}